{"name":"Face-To-Transform-Orientation","tagline":"Blender add-on: Face object to transform orientation","body":"# Blender Add-on \"Face to Transform Orientation\"\r\n\r\nThis is a blender add-on \"Face to Transform Orientation\".\r\nThis addon can face object to registered transform orientation.\r\n\r\n## Release URL\r\n\r\n|Version|Download URL|\r\n|---|---|\r\n|0.2|[Download](https://github.com/nutti/Face-To-Transform-Orientation/tag/v0.2)|\r\n|0.1|[Download](https://github.com/nutti/Face-To-Transform-Orientation/tag/v0.1)|\r\n\r\n## Support languages\r\n\r\n**English** only.\r\n\r\n## Features\r\n\r\nThis add-on's features are as follows.\r\n\r\n* Face object to registered transform orientation.\r\n\r\n## Tutorials\r\n\r\n### Merge nearest neighbor vertex by mouse clicking\r\n\r\n1. Create transform orientation from the menu appeared by pressing key **N**.\r\n2. Click menu **Object** - **Transform**\r\n3. Click **Face to Transform Orientation**\r\n4. You can change transform orientation and rotation angle by changing 'tools property'\r\n\r\n[![](http://img.youtube.com/vi/zOaNawzJWC4/0.jpg)](https://www.youtube.com/watch?v=zOaNawzJWC4)\r\n\r\n## Related Links\r\n\r\n* [Blender Artist](http://blenderartists.org/forum/showthread.php?367639-Addon-Face-object-to-Transform-Orientation)\r\n* [D.B.O T44454](https://developer.blender.org/T44279)\r\n* [Google+](https://plus.google.com/100058529622539760372/posts/LscGEa2AWK7)\r\n\r\n## Change Log\r\n|Version|Release Date|Change Log|\r\n|---|---|---|\r\n|0.2|2015.5.17|**Change feature**<br>1. Move menu to 'Object' - 'Transform' - 'Face To Transform Orientation'<br>2. Apply transformation to selected objects instead of active object.|\r\n|0.1|2015.3.28|First release.|\r\n\r\n## Bug report / Feature request\r\n\r\nThis addon's project is in progress.\r\nIf you want to report problem or request feature, please make issues.\r\n\r\n## Contribution\r\n\r\nIf you want to contribute this project, please send pull request to **develop** branch.\r\nhttps://github.com/nutti/Face-To-Transform-Orientation/tree/develop\r\n**DO NOT** send pull request to **master** branch. \r\n","google":"","note":"Don't delete this file! It's used internally to help with page regeneration."}